furiosa_torch_ext/__init__.py
furiosa_torch_ext/git_version.txt
furiosa_torch_ext/torch_ext.py
furiosa_torch_ext-2025.3.1.dist-info/WHEEL
furiosa_torch_ext-2025.3.1.dist-info/METADATA
furiosa_torch_ext-2025.3.1.dist-info/RECORD
